cog_hf_template/__init__.py
cog_hf_template/cli.py
cog_hf_template/download_utils.py
cog_hf_template/hf.py
cog_hf_template/main.py
cog_hf_template/sbert.py
cog_hf_template/text_generation.py
cog_hf_template-0.0.13.dist-info/LICENSE
cog_hf_template-0.0.13.dist-info/METADATA
cog_hf_template-0.0.13.dist-info/WHEEL
cog_hf_template-0.0.13.dist-info/entry_points.txt
cog_hf_template-0.0.13.dist-info/top_level.txt
cog_hf_template-0.0.13.dist-info/RECORD
