Metadata-Version: 2.1
Name: cog-hf-template
Version: 0.0.13
Summary: Cog template for Hugging Face.
Author: Nathan Raw
Author-email: naterawdata@gmail.com
License: Apache
License-File: LICENSE
Requires-Dist: cog
Requires-Dist: torch ==2.0.1
Requires-Dist: torchvision ==0.15.2
Requires-Dist: transformers >=4.33.2
Requires-Dist: sentencepiece >=0.1.99
Requires-Dist: accelerate >=0.22.0
Requires-Dist: scipy >=1.10.1
Requires-Dist: protobuf ==3.20.3
Requires-Dist: Pillow >=10.1.0
Requires-Dist: bitsandbytes >=0.41.1
Requires-Dist: sentence-transformers >=2.2.2
Provides-Extra: all
Requires-Dist: black ; extra == 'all'
Requires-Dist: ruff ; extra == 'all'
Requires-Dist: google-cloud-storage ; extra == 'all'
Requires-Dist: fire ; extra == 'all'
Provides-Extra: cli
Requires-Dist: fire ; extra == 'cli'
Provides-Extra: dev
Requires-Dist: black ; extra == 'dev'
Requires-Dist: ruff ; extra == 'dev'
Provides-Extra: gcp
Requires-Dist: google-cloud-storage ; extra == 'gcp'
